{
  "name": "Hospital",
  "path": "Service--Medical--Hospital",
  "fields": [
    "name",
    "nps/unitcode",
    "operator",
    "address",
    "opening_hours",
    "emergency"
  ],
  "geometry": [
    "point"
  ],
  "icon": "hospital-black",
  "maki": "npmap-symbol-library",
  "layerIndex": 10,
  "defaultOrder": null,
  "matchScore": 1,
  "inCarto": true,
  "inGuide": true,
  "inEditor": true,
  "tags": {
    "amenity": "hospital"
  },
  "terms": [
    "doctor",
    "emergency room",
    "health service",
    "hospital grounds",
    "institution",
    "infirmary",
    "medical",
    "sick",
    "surgery",
    "ward",
    "emergency",
    "clinic"
  ]
}