{
  "name": "Motorized Watercraft Trail",
  "path": "Trail--Motorized--Motorized_Watercraft_Trail",
  "fields": [
    "name",
    "nps/unitcode",
    "operator",
    "whitewater",
    "width",
    "section_grade",
    "nps/wateruse"
  ],
  "geometry": [
    "line"
  ],
  "matchScore": 10,
  "tags": {
    "motorboat": "yes",
    "waterway": "yes"
  },
  "terms": [
    "motorized watercraft trail",
    "motorized watercraft",
    "motorboat",
    "trail",
    "track"
  ],
  "gisTags": {
    "OSM_Line": "x",
    "JSON_Icon_Line": "highway-track",
    "Trail": "Yes",
    "Trail_Values": "{\"TRLFEATTYPE\":\"Park Trail\",\"TRLSTATUS\":\"Existing\",\"TRLTYPE\":\"Unknown\",\"TRLUSE_MOTORBOAT\":\"Yes\"}",
    "Trail_OSM_Tags": "{\"name\",\"surface\",\"tracktype\"}",
    "Trail_GIS_Tags": "{\"TRLNAME\",\"TRLSURFACE\",\"TRLCLASS\"}"
  }
}